pybricksdev/__init__.py
pybricksdev/__main__.py
pybricksdev/_vendored/dfu_create.py
pybricksdev/_vendored/dfu_upload.py
pybricksdev/_vendored/pynxt/__init__.py
pybricksdev/_vendored/pynxt/firmware.py
pybricksdev/_vendored/pynxt/flash.py
pybricksdev/_vendored/pynxt/lowlevel.py
pybricksdev/_vendored/pynxt/resources/Makefile
pybricksdev/_vendored/pynxt/resources/__init__.py
pybricksdev/_vendored/pynxt/resources/crt0.s
pybricksdev/_vendored/pynxt/resources/flash.c
pybricksdev/_vendored/pynxt/resources/flash_driver.bin
pybricksdev/_vendored/pynxt/samba.py
pybricksdev/ble/__init__.py
pybricksdev/ble/lwp3/__init__.py
pybricksdev/ble/lwp3/bootloader.py
pybricksdev/ble/lwp3/bytecodes.py
pybricksdev/ble/lwp3/messages.py
pybricksdev/ble/nus.py
pybricksdev/ble/oad/__init__.py
pybricksdev/ble/oad/_common.py
pybricksdev/ble/oad/control_point.py
pybricksdev/ble/oad/firmware.py
pybricksdev/ble/oad/image_block.py
pybricksdev/ble/oad/image_identify.py
pybricksdev/ble/pybricks.py
pybricksdev/cli/__init__.py
pybricksdev/cli/flash.py
pybricksdev/cli/lwp3/__init__.py
pybricksdev/cli/lwp3/repl.py
pybricksdev/cli/oad.py
pybricksdev/compile.py
pybricksdev/connections/__init__.py
pybricksdev/connections/ev3.py
pybricksdev/connections/pybricks.py
pybricksdev/dfu.py
pybricksdev/firmware.py
pybricksdev/flash.py
pybricksdev/resources/99-pybricksdev.rules
pybricksdev/resources/__init__.py
pybricksdev/resources/dfu-util.exe
pybricksdev/resources/libusb-1.0.dll
pybricksdev/tools/__init__.py
pybricksdev/tools/checksum.py
pybricksdev/usb/__init__.py
pybricksdev/usb/pybricks.py
pybricksdev-2.1.1.dist-info/AUTHORS.md
pybricksdev-2.1.1.dist-info/LICENSE
pybricksdev-2.1.1.dist-info/METADATA
pybricksdev-2.1.1.dist-info/WHEEL
pybricksdev-2.1.1.dist-info/entry_points.txt
pybricksdev-2.1.1.dist-info/RECORD
