Metadata-Version: 2.3
Name: pybricksdev
Version: 2.1.1
Summary: Pybricks developer tools
License: MIT
Author: The Pybricks Authors
Author-email: dev@pybricks.com
Maintainer: Laurens Valk
Maintainer-email: laurens@pybricks.com
Requires-Python: >=3.10
Classifier: Intended Audience :: Developers
Classifier: Natural Language :: English
Classifier: Operating System :: OS Independent
Requires-Dist: appdirs (>=1.4.4)
Requires-Dist: argcomplete (>=3.6.2)
Requires-Dist: bleak (>=1.1.0)
Requires-Dist: hidapi (>=0.14.0)
Requires-Dist: mpy-cross-v5 (>=1.1.1)
Requires-Dist: mpy-cross-v6 (>=1.1.1)
Requires-Dist: packaging (>=22)
Requires-Dist: prompt-toolkit (>=3.0.18)
Requires-Dist: pybricks (>=3) ; python_version < "4"
Requires-Dist: pyusb (>=1.0.2)
Requires-Dist: questionary (>=2.1.1) ; python_version < "4"
Requires-Dist: reactivex (>=4.0.4) ; python_version < "4"
Requires-Dist: semver (>=2.13.0)
Requires-Dist: tqdm (>=4.62.3)
Requires-Dist: typing-extensions (>=4.3.0)
Project-URL: Changelog, https://github.com/pybricks/pybricksdev/blob/master/CHANGELOG.md
Project-URL: Documentation, https://docs.pybricks.com/projects/pybricksdev
Project-URL: Homepage, https://pybricks.com
Project-URL: Issues, https://github.com/pybricks/support/issues
Project-URL: Repository, https://github.com/pybricks/pybricksdev
Project-URL: Support, https://github.com/pybricks/support/discussions
